D365FW/Access.py
D365FW/Common.py
D365FW/Constant.py
D365FW/D365FW.py
D365FW/Entity.py
D365FW/__init__.py
D365FW/Test/TestAccess.py
D365FW/Test/TestAccount.py
D365FW/Test/TestD365FW.py
D365FW/Test/__init__.py
d365fw-0.8.2.dist-info/LICENSE
d365fw-0.8.2.dist-info/METADATA
d365fw-0.8.2.dist-info/WHEEL
d365fw-0.8.2.dist-info/top_level.txt
d365fw-0.8.2.dist-info/RECORD
