Metadata-Version: 2.1
Name: d365fw
Version: 0.8.2
Summary: Microsoft Dynamics 365 FrameWork.
Author: Yan Kuang
Author-email: YTKme@Outlook.com
License: GNU GENERAL PUBLIC LICENSE
Keywords: dynamics d365 fw api microsoft
Platform: UNKNOWN
License-File: LICENSE
Requires-Dist: requests
